pycalc_uuid7/__init__.py
pycalc_uuid7/uuid7.py
pycalc_uuid7-0.0.2.dist-info/LICENSE
pycalc_uuid7-0.0.2.dist-info/METADATA
pycalc_uuid7-0.0.2.dist-info/WHEEL
pycalc_uuid7-0.0.2.dist-info/top_level.txt
pycalc_uuid7-0.0.2.dist-info/RECORD
